Products.MeetingPROVHainaut-4.2.3-py3.12-nspkg.pth
Products/MeetingPROVHainaut/__init__.py
Products/MeetingPROVHainaut/adapters.py
Products/MeetingPROVHainaut/config.py
Products/MeetingPROVHainaut/configure.zcml
Products/MeetingPROVHainaut/events.py
Products/MeetingPROVHainaut/events.zcml
Products/MeetingPROVHainaut/interfaces.py
Products/MeetingPROVHainaut/overrides.zcml
Products/MeetingPROVHainaut/profiles.zcml
Products/MeetingPROVHainaut/setuphandlers.py
Products/MeetingPROVHainaut/testing.py
Products/MeetingPROVHainaut/testing.zcml
Products/MeetingPROVHainaut/utils.py
Products/MeetingPROVHainaut/Extensions/__init__.py
Products/MeetingPROVHainaut/Extensions/utils.py
Products/MeetingPROVHainaut/browser/__init__.py
Products/MeetingPROVHainaut/browser/overrides.py
Products/MeetingPROVHainaut/faceted_conf/meetingprovhainaut_dashboard_items_widgets.xml
Products/MeetingPROVHainaut/locales/PloneMeeting.pot
Products/MeetingPROVHainaut/locales/plone.pot
Products/MeetingPROVHainaut/locales/sync_pos.sh
Products/MeetingPROVHainaut/locales/en/LC_MESSAGES/PloneMeeting.po
Products/MeetingPROVHainaut/locales/en/LC_MESSAGES/plone.po
Products/MeetingPROVHainaut/locales/fr/LC_MESSAGES/PloneMeeting.po
Products/MeetingPROVHainaut/locales/fr/LC_MESSAGES/plone.po
Products/MeetingPROVHainaut/migrations/__init__.py
Products/MeetingPROVHainaut/migrations/migrate_to_4200.py
Products/MeetingPROVHainaut/migrations/migrate_to_4201.py
Products/MeetingPROVHainaut/migrations/migrate_to_4202.py
Products/MeetingPROVHainaut/migrations/migrate_to_4203.py
Products/MeetingPROVHainaut/migrations/migrate_to_4204.py
Products/MeetingPROVHainaut/profiles/__init__.py
Products/MeetingPROVHainaut/profiles/default/MeetingPROVHainaut_marker.txt
Products/MeetingPROVHainaut/profiles/default/__init__.py
Products/MeetingPROVHainaut/profiles/default/cssregistry.xml
Products/MeetingPROVHainaut/profiles/default/import_steps.xml
Products/MeetingPROVHainaut/profiles/default/metadata.xml
products_meetingprovhainaut-4.2.3.dist-info/METADATA
products_meetingprovhainaut-4.2.3.dist-info/WHEEL
products_meetingprovhainaut-4.2.3.dist-info/namespace_packages.txt
products_meetingprovhainaut-4.2.3.dist-info/top_level.txt
products_meetingprovhainaut-4.2.3.dist-info/RECORD
