Metadata-Version: 2.4
Name: Products.MeetingPROVHainaut
Version: 4.2.3
Summary: PloneMeeting profile for Province de Hainaut
Home-page: https://www.imio.be/nos-applications/ia-delib
Author: Gauthier Bastien
Author-email: gauthier@imio.be
License: GPL
Keywords: plone official meetings management egov communesplone imio plonegov hainaut
Classifier: Development Status :: 6 - Mature
Classifier: Environment :: Web Environment
Classifier: Framework :: Plone
Classifier: Framework :: Plone :: 4.3
Classifier: Intended Audience :: Customer Service
Classifier: Intended Audience :: Developers
Classifier: Intended Audience :: End Users/Desktop
Classifier: License :: OSI Approved :: GNU General Public License (GPL)
Classifier: Operating System :: OS Independent
Classifier: Programming Language :: Other Scripting Engines
Classifier: Programming Language :: Python
Classifier: Programming Language :: Python :: 2.7
Classifier: Topic :: Internet :: WWW/HTTP :: Site Management
Classifier: Topic :: Software Development :: Libraries :: Python Modules
Classifier: Topic :: Office/Business
Requires-Dist: Products.MeetingCommunes
Provides-Extra: test
Requires-Dist: Products.PloneMeeting[test]; extra == "test"
Dynamic: author
Dynamic: author-email
Dynamic: classifier
Dynamic: description
Dynamic: home-page
Dynamic: keywords
Dynamic: license
Dynamic: provides-extra
Dynamic: requires-dist
Dynamic: summary
